src/__init__.py
src/main.py
tests/__init__.py
tests/test_add.py
pomares_optativa_pycicd-1.0.3.dist-info/METADATA
pomares_optativa_pycicd-1.0.3.dist-info/WHEEL
pomares_optativa_pycicd-1.0.3.dist-info/top_level.txt
pomares_optativa_pycicd-1.0.3.dist-info/RECORD
