Metadata-Version: 2.4
Name: pomares_optativa_PyCiCd
Version: 1.0.3
Summary: Proyecto de practica
Author: Javier Pomares Gomez
Author-email: javierpomaresgomez@gmail.com
Requires-Dist: pytest
Requires-Dist: flake8
Dynamic: author
Dynamic: author-email
Dynamic: requires-dist
Dynamic: summary
